LICENSE.txt
README.md
setup.py
caches/__init__.py
caches/compat.py
caches/core.py
caches/decorators.py
caches/dsn.py
caches/exception.py
caches/interface.py
caches.egg-info/PKG-INFO
caches.egg-info/SOURCES.txt
caches.egg-info/dependency_links.txt
caches.egg-info/requires.txt
caches.egg-info/top_level.txt
tests/__init__.py
tests/caches_test.py
tests/core_test.py
tests/decorators_test.py
tests/dsn_test.py