Metadata-Version: 2.1
Name: caches
Version: 3.0.0
Summary: Python caching backed by Redis
Home-page: http://github.com/jaymon/caches
Author: Jay Marcyes
Author-email: jay@marcyes.com
License: MIT
Classifier: Development Status :: 5 - Production/Stable
Classifier: Environment :: Web Environment
Classifier: Intended Audience :: Developers
Classifier: License :: OSI Approved :: MIT License
Classifier: Operating System :: OS Independent
Classifier: Topic :: Database
Classifier: Topic :: Software Development :: Libraries
Classifier: Topic :: Utilities
Classifier: Programming Language :: Python :: 3 :: Only
Classifier: Programming Language :: Python :: 3.10
License-File: LICENSE.txt
